logica_desvios/__init__.py
logica_desvios/agente_inteligente.py
logica_desvios/circuit_breaker.py
logica_desvios/decision_maker.py
logica_desvios/machine_learning_adapter.py
logica_desvios-0.3.0.dist-info/licenses/LICENSE
logica_desvios-0.3.0.dist-info/METADATA
logica_desvios-0.3.0.dist-info/WHEEL
logica_desvios-0.3.0.dist-info/entry_points.txt
logica_desvios-0.3.0.dist-info/top_level.txt
logica_desvios-0.3.0.dist-info/RECORD
