Metadata-Version: 2.4
Name: logica-desvios
Version: 0.3.0
Summary: Circuit Breaker inteligente com Machine Learning adaptativo
Home-page: https://github.com/WSS13Framework/curso-automacao-linux-resiliente-limpo
Author: Marcos Sea
Author-email: Marcos Sea <socramsea@hotmail.com>
Maintainer-email: Marcos Sea <socramsea@hotmail.com>
License: MIT
Project-URL: Homepage, https://github.com/socramsea/logica-desvios
Project-URL: Documentation, https://github.com/socramsea/logica-desvios#readme
Project-URL: Repository, https://github.com/socramsea/logica-desvios
Project-URL: Issues, https://github.com/socramsea/logica-desvios/issues
Project-URL: Changelog, https://github.com/socramsea/logica-desvios/blob/main/CHANGELOG.md
Keywords: circuit-breaker,resilience,machine-learning,adaptive,fault-tolerance,microservices,reliability
Classifier: Development Status :: 4 - Beta
Classifier: Intended Audience :: Developers
Classifier: Topic :: Software Development :: Libraries :: Python Modules
Classifier: License :: OSI Approved :: MIT License
Classifier: Programming Language :: Python :: 3
Classifier: Programming Language :: Python :: 3.7
Classifier: Programming Language :: Python :: 3.8
Classifier: Programming Language :: Python :: 3.9
Classifier: Programming Language :: Python :: 3.10
Classifier: Programming Language :: Python :: 3.11
Classifier: Programming Language :: Python :: 3.12
Classifier: Operating System :: OS Independent
Requires-Python: >=3.8
License-File: LICENSE
Requires-Dist: pandas>=1.0.0
Requires-Dist: numpy>=1.18.0
Provides-Extra: dev
Requires-Dist: pytest>=6.0; extra == "dev"
Requires-Dist: pytest-cov>=2.0; extra == "dev"
Requires-Dist: black>=21.0; extra == "dev"
Requires-Dist: flake8>=3.9; extra == "dev"
Requires-Dist: mypy>=0.900; extra == "dev"
Requires-Dist: twine>=4.0; extra == "dev"
Provides-Extra: ml
Requires-Dist: scikit-learn>=0.24.0; extra == "ml"
Dynamic: author
Dynamic: home-page
Dynamic: license-file
Dynamic: requires-python
